cmdlineobserver/README.MD
cmdlineobserver/__init__.py
cmdlineobserver/requirements.txt
cmdlineobserver/thirdparty.json
cmdlineobserver-0.10.dist-info/LICENSE.rst
cmdlineobserver-0.10.dist-info/METADATA
cmdlineobserver-0.10.dist-info/WHEEL
cmdlineobserver-0.10.dist-info/top_level.txt
cmdlineobserver-0.10.dist-info/RECORD
