Metadata-Version: 2.1
Name: cmdlineobserver
Version: 0.10
Summary: Monitors and observes running processes with their command line details.
Home-page: https://github.com/hansalemaos/cmdlineobserver
Author: Johannes Fischer
Author-email: aulasparticularesdealemaosp@gmail.com
License: MIT
Keywords: process,observer,cmdline
Classifier: Development Status :: 4 - Beta
Classifier: Programming Language :: Python :: 3 :: Only
Classifier: Programming Language :: Python :: 3.10
Classifier: Topic :: Software Development :: Libraries :: Python Modules
Classifier: Topic :: Utilities
License-File: LICENSE.rst
Requires-Dist: getproclist
Requires-Dist: pandas
Requires-Dist: touchtouch
